dbt_schema_generator/__init__.py
dbt_schema_generator/generator.py
dbt_schema_generator-0.1.1a2.dist-info/LICENSE
dbt_schema_generator-0.1.1a2.dist-info/METADATA
dbt_schema_generator-0.1.1a2.dist-info/WHEEL
dbt_schema_generator-0.1.1a2.dist-info/entry_points.txt
dbt_schema_generator-0.1.1a2.dist-info/top_level.txt
dbt_schema_generator-0.1.1a2.dist-info/RECORD
