Metadata-Version: 2.1
Name: dbt-schema-generator
Version: 0.1.1a2
Summary: A command-line tool to generate schema.yml files for specified dbt models
Home-page: https://github.com/Muizzkolapo/dbt_schema_generator.git
Author: Your Name
Author-email: lateefmuizz@gmail.com
License: MIT
Classifier: Development Status :: 3 - Alpha
Classifier: License :: OSI Approved :: MIT License
Classifier: Programming Language :: Python :: 3
Classifier: Programming Language :: Python :: 3.9
Requires-Python: >=3.9
License-File: LICENSE
